{"extended_tweet":{"extended_entities":{"media":[{"display_url":"pic.twitter.com/7h3VB7IzYN","indices":[297,320],"sizes":{"small":{"w":383,"h":680,"resize":"fit"},"large":{"w":1152,"h":2048,"resize":"fit"},"thumb":{"w":150,"h":150,"resize":"crop"},"medium":{"w":675,"h":1200,"resize":"fit"}},"id_str":"1105908561199144960","expanded_url":"https://twitter.com/SpeakTheEnglish/status/1105908567629090816/photo/1","media_url_https":"https://pbs.twimg.com/media/D1j5-iBWoAAV3pt.jpg","id":1105908561199144960,"type":"photo","media_url":"http://pbs.twimg.com/media/D1j5-iBWoAAV3pt.jpg","url":"https://t.co/7h3VB7IzYN"}]},"entities":{"urls":[],"hashtags":[],"media":[{"display_url":"pic.twitter.com/7h3VB7IzYN","indices":[297,320],"sizes":{"small":{"w":383,"h":680,"resize":"fit"},"large":{"w":1152,"h":2048,"resize":"fit"},"thumb":{"w":150,"h":150,"resize":"crop"},"medium":{"w":675,"h":1200,"resize":"fit"}},"id_str":"1105908561199144960","expanded_url":"https://twitter.com/SpeakTheEnglish/status/1105908567629090816/photo/1","media_url_https":"https://pbs.twimg.com/media/D1j5-iBWoAAV3pt.jpg","id":1105908561199144960,"type":"photo","media_url":"http://pbs.twimg.com/media/D1j5-iBWoAAV3pt.jpg","url":"https://t.co/7h3VB7IzYN"}],"user_mentions":[{"indices":[0,11],"screen_name":"WhiteHouse","id_str":"822215673812119553","name":"The White House","id":822215673812119553},{"indices":[12,16],"screen_name":"CBP","id_str":"16613128","name":"CBP","id":16613128},{"indices":[154,161],"screen_name":"DHSgov","id_str":"15647676","name":"Homeland Security","id":15647676},{"indices":[162,166],"screen_name":"CBP","id_str":"16613128","name":"CBP","id":16613128}],"symbols":[]},"full_text":"@WhiteHouse @CBP Did you check the White House/CBP for the same types of vermin? I\u2019m not sure you\u2019re watching the congressional hearings but, sounds like @DHSgov @CBP has an issue w/these types w/in their ranks &amp; or  \u201ccontract workers\u201d. How many unaccompanied women/children sexual assaulted? https://t.co/7h3VB7IzYN","display_text_range":[17,296]},"in_reply_to_status_id_str":"1105851258571759617","in_reply_to_status_id":1105851258571759617,"created_at":"Wed Mar 13 19:08:43 +0000 2019","in_reply_to_user_id_str":"822215673812119553","source":"<a href=\"http://twitter.com/download/iphone\" rel=\"nofollow\">Twitter for iPhone<\/a>","retweet_count":0,"retweeted":false,"geo":null,"filter_level":"low","in_reply_to_screen_name":"WhiteHouse","is_quote_status":false,"id_str":"1105908567629090816","in_reply_to_user_id":822215673812119553,"favorite_count":0,"id":1105908567629090816,"text":"@WhiteHouse @CBP Did you check the White House/CBP for the same types of vermin? I\u2019m not sure you\u2019re watching the c\u2026 https://t.co/1f5Pn9Ioax","place":{"country_code":"ES","country":"Spain","full_name":"Madrid, Spain","bounding_box":{"coordinates":[[[-3.889005,40.312071],[-3.889005,40.643518],[-3.51801,40.643518],[-3.51801,40.312071]]],"type":"Polygon"},"place_type":"city","name":"Madrid","attributes":{},"id":"206c436ce43a43a3","url":"https://api.twitter.com/1.1/geo/id/206c436ce43a43a3.json"},"lang":"en","quote_count":0,"favorited":false,"possibly_sensitive":false,"coordinates":null,"truncated":true,"timestamp_ms":"1552504123967","reply_count":0,"entities":{"urls":[{"display_url":"twitter.com/i/web/status/1\u2026","indices":[117,140],"expanded_url":"https://twitter.com/i/web/status/1105908567629090816","url":"https://t.co/1f5Pn9Ioax"}],"hashtags":[],"user_mentions":[{"indices":[0,11],"screen_name":"WhiteHouse","id_str":"822215673812119553","name":"The White House","id":822215673812119553},{"indices":[12,16],"screen_name":"CBP","id_str":"16613128","name":"CBP","id":16613128}],"symbols":[]},"display_text_range":[17,140],"contributors":null,"user":{"utc_offset":null,"friends_count":61,"profile_image_url_https":"https://pbs.twimg.com/profile_images/871059948482035713/xIrilXkN_normal.jpg","listed_count":0,"profile_background_image_url":"http://abs.twimg.com/images/themes/theme1/bg.png","default_profile_image":false,"favourites_count":2729,"description":"spēk thē ĭng\u2032glĭsh SPEAK THE ENGLISH","created_at":"Thu May 29 13:10:36 +0000 2014","is_translator":false,"profile_background_image_url_https":"https://abs.twimg.com/images/themes/theme1/bg.png","protected":false,"screen_name":"SpeakTheEnglish","id_str":"2532644551","profile_link_color":"7FDBB6","translator_type":"none","id":2532644551,"geo_enabled":true,"profile_background_color":"C0DEED","lang":"en","profile_sidebar_border_color":"C0DEED","profile_text_color":"333333","verified":false,"profile_image_url":"http://pbs.twimg.com/profile_images/871059948482035713/xIrilXkN_normal.jpg","time_zone":null,"url":"http://www.speaktheenglish.com","contributors_enabled":false,"profile_background_tile":false,"profile_banner_url":"https://pbs.twimg.com/profile_banners/2532644551/1508795310","statuses_count":3375,"follow_request_sent":null,"followers_count":28,"profile_use_background_image":true,"default_profile":false,"following":null,"name":"SpeakTheEnglish","location":"Madrid, Spain","profile_sidebar_fill_color":"DDEEF6","notifications":null}}