{"extended_tweet":{"extended_entities":{"media":[{"display_url":"pic.twitter.com/Rb3X2ZgptB","indices":[137,160],"sizes":{"small":{"w":680,"h":331,"resize":"fit"},"large":{"w":2048,"h":996,"resize":"fit"},"thumb":{"w":150,"h":150,"resize":"crop"},"medium":{"w":1200,"h":584,"resize":"fit"}},"id_str":"1105901272786448389","expanded_url":"https://twitter.com/rociorllopis/status/1105901295246999555/photo/1","media_url_https":"https://pbs.twimg.com/media/D1jzWSkWsAUTUle.jpg","id":1105901272786448389,"type":"photo","media_url":"http://pbs.twimg.com/media/D1jzWSkWsAUTUle.jpg","url":"https://t.co/Rb3X2ZgptB"}]},"entities":{"urls":[],"hashtags":[{"indices":[4,16],"text":"MeetOctober"},{"indices":[29,38],"text":"startups"}],"media":[{"display_url":"pic.twitter.com/Rb3X2ZgptB","indices":[137,160],"sizes":{"small":{"w":680,"h":331,"resize":"fit"},"large":{"w":2048,"h":996,"resize":"fit"},"thumb":{"w":150,"h":150,"resize":"crop"},"medium":{"w":1200,"h":584,"resize":"fit"}},"id_str":"1105901272786448389","expanded_url":"https://twitter.com/rociorllopis/status/1105901295246999555/photo/1","media_url_https":"https://pbs.twimg.com/media/D1jzWSkWsAUTUle.jpg","id":1105901272786448389,"type":"photo","media_url":"http://pbs.twimg.com/media/D1jzWSkWsAUTUle.jpg","url":"https://t.co/Rb3X2ZgptB"}],"user_mentions":[{"indices":[43,58],"screen_name":"camille__david","id_str":"885817142335164416","name":"Camille David","id":885817142335164416},{"indices":[60,72],"screen_name":"borrellpepe","id_str":"220963656","name":"Pepe Borrell","id":220963656},{"indices":[74,82],"screen_name":"WayraES","id_str":"465657021","name":"Wayra España","id":465657021},{"indices":[83,99],"screen_name":"WaveApplication","id_str":"1583833814","name":"Wave","id":1583833814},{"indices":[100,114],"screen_name":"SeayaVentures","id_str":"1019616104535207936","name":"SeayaVentures","id":1019616104535207936},{"indices":[121,136],"screen_name":"BBVAInnovation","id_str":"14157408","name":"BBVA Open Innovation","id":14157408}],"symbols":[]},"full_text":"3rd #MeetOctober sobre VCs y #startups con @camille__david, @borrellpepe, @WayraES @WaveApplication @SeayaVentures en el @BBVAInnovation https://t.co/Rb3X2ZgptB","display_text_range":[0,136]},"in_reply_to_status_id_str":null,"in_reply_to_status_id":null,"created_at":"Wed Mar 13 18:39:50 +0000 2019","in_reply_to_user_id_str":null,"source":"<a href=\"http://twitter.com/download/android\" rel=\"nofollow\">Twitter for Android<\/a>","retweet_count":0,"retweeted":false,"geo":null,"filter_level":"low","in_reply_to_screen_name":null,"is_quote_status":false,"id_str":"1105901295246999555","in_reply_to_user_id":null,"favorite_count":0,"id":1105901295246999555,"text":"3rd #MeetOctober sobre VCs y #startups con @camille__david, @borrellpepe, @WayraES @WaveApplication @SeayaVentures\u2026 https://t.co/pDsfNY7b46","place":{"country_code":"ES","country":"España","full_name":"Centro de Innovación BBVA","bounding_box":{"coordinates":[[[-3.696972,40.427264],[-3.696972,40.427264],[-3.696972,40.427264],[-3.696972,40.427264]]],"type":"Polygon"},"place_type":"poi","name":"Centro de Innovación BBVA","attributes":{},"id":"07d9e66231084000","url":"https://api.twitter.com/1.1/geo/id/07d9e66231084000.json"},"lang":"es","quote_count":0,"favorited":false,"possibly_sensitive":false,"coordinates":null,"truncated":true,"timestamp_ms":"1552502390096","reply_count":0,"entities":{"urls":[{"display_url":"twitter.com/i/web/status/1\u2026","indices":[116,139],"expanded_url":"https://twitter.com/i/web/status/1105901295246999555","url":"https://t.co/pDsfNY7b46"}],"hashtags":[{"indices":[4,16],"text":"MeetOctober"},{"indices":[29,38],"text":"startups"}],"user_mentions":[{"indices":[43,58],"screen_name":"camille__david","id_str":"885817142335164416","name":"Camille David","id":885817142335164416},{"indices":[60,72],"screen_name":"borrellpepe","id_str":"220963656","name":"Pepe Borrell","id":220963656},{"indices":[74,82],"screen_name":"WayraES","id_str":"465657021","name":"Wayra España","id":465657021},{"indices":[83,99],"screen_name":"WaveApplication","id_str":"1583833814","name":"Wave","id":1583833814},{"indices":[100,114],"screen_name":"SeayaVentures","id_str":"1019616104535207936","name":"SeayaVentures","id":1019616104535207936}],"symbols":[]},"display_text_range":[0,140],"contributors":null,"user":{"utc_offset":null,"friends_count":449,"profile_image_url_https":"https://pbs.twimg.com/profile_images/985800657096540160/BgaBdLou_normal.jpg","listed_count":39,"profile_background_image_url":"http://abs.twimg.com/images/themes/theme15/bg.png","default_profile_image":false,"favourites_count":944,"description":"startups, marketing and food","created_at":"Wed Apr 20 16:08:54 +0000 2011","is_translator":false,"profile_background_image_url_https":"https://abs.twimg.com/images/themes/theme15/bg.png","protected":false,"screen_name":"rociorllopis","id_str":"285140369","profile_link_color":"0084B4","translator_type":"none","id":285140369,"geo_enabled":true,"profile_background_color":"022330","lang":"es","profile_sidebar_border_color":"A8C7F7","profile_text_color":"333333","verified":false,"profile_image_url":"http://pbs.twimg.com/profile_images/985800657096540160/BgaBdLou_normal.jpg","time_zone":null,"url":null,"contributors_enabled":false,"profile_background_tile":false,"profile_banner_url":"https://pbs.twimg.com/profile_banners/285140369/1480266563","statuses_count":501,"follow_request_sent":null,"followers_count":375,"profile_use_background_image":true,"default_profile":false,"following":null,"name":"Rocío R. Llopis","location":"Madrid","profile_sidebar_fill_color":"C0DFEC","notifications":null}}