{"quoted_status":{"extended_entities":{"media":[{"display_url":"pic.twitter.com/kCzzaDKN3n","indices":[19,42],"sizes":{"small":{"w":400,"h":400,"resize":"fit"},"large":{"w":400,"h":400,"resize":"fit"},"thumb":{"w":150,"h":150,"resize":"crop"},"medium":{"w":400,"h":400,"resize":"fit"}},"id_str":"1104798177578926081","expanded_url":"https://twitter.com/Unexplained/status/1104798247028224001/video/1","media_url_https":"https://pbs.twimg.com/ext_tw_video_thumb/1104798177578926081/pu/img/MdN_7dpcAv5zKCdq.jpg","id":1104798177578926081,"additional_media_info":{"monetizable":false},"type":"video","media_url":"http://pbs.twimg.com/ext_tw_video_thumb/1104798177578926081/pu/img/MdN_7dpcAv5zKCdq.jpg","url":"https://t.co/kCzzaDKN3n","video_info":{"aspect_ratio":[1,1],"duration_millis":92508,"variants":[{"content_type":"video/mp4","bitrate":832000,"url":"https://video.twimg.com/ext_tw_video/1104798177578926081/pu/vid/400x400/0p7OrNDoHjSG3ISn.mp4?tag=8"},{"content_type":"video/mp4","bitrate":432000,"url":"https://video.twimg.com/ext_tw_video/1104798177578926081/pu/vid/320x320/ZM_ckfGQ0qMV-7xS.mp4?tag=8"},{"content_type":"application/x-mpegURL","url":"https://video.twimg.com/ext_tw_video/1104798177578926081/pu/pl/bKHjnU-1wPWIO_wE.m3u8?tag=8"}]}}]},"in_reply_to_status_id_str":null,"in_reply_to_status_id":null,"created_at":"Sun Mar 10 17:36:42 +0000 2019","in_reply_to_user_id_str":null,"source":"<a href=\"http://twitter.com/download/iphone\" rel=\"nofollow\">Twitter for iPhone<\/a>","retweet_count":24627,"retweeted":false,"geo":null,"filter_level":"low","in_reply_to_screen_name":null,"is_quote_status":false,"id_str":"1104798247028224001","in_reply_to_user_id":null,"favorite_count":62538,"id":1104798247028224001,"text":"Watch your step 😳🏖 https://t.co/kCzzaDKN3n","place":null,"lang":"en","quote_count":31896,"favorited":false,"possibly_sensitive":true,"coordinates":null,"truncated":false,"reply_count":2984,"entities":{"urls":[],"hashtags":[],"media":[{"display_url":"pic.twitter.com/kCzzaDKN3n","indices":[19,42],"sizes":{"small":{"w":400,"h":400,"resize":"fit"},"large":{"w":400,"h":400,"resize":"fit"},"thumb":{"w":150,"h":150,"resize":"crop"},"medium":{"w":400,"h":400,"resize":"fit"}},"id_str":"1104798177578926081","expanded_url":"https://twitter.com/Unexplained/status/1104798247028224001/video/1","media_url_https":"https://pbs.twimg.com/ext_tw_video_thumb/1104798177578926081/pu/img/MdN_7dpcAv5zKCdq.jpg","id":1104798177578926081,"additional_media_info":{"monetizable":false},"type":"photo","media_url":"http://pbs.twimg.com/ext_tw_video_thumb/1104798177578926081/pu/img/MdN_7dpcAv5zKCdq.jpg","url":"https://t.co/kCzzaDKN3n"}],"user_mentions":[],"symbols":[]},"display_text_range":[0,18],"contributors":null,"user":{"utc_offset":null,"friends_count":546,"profile_image_url_https":"https://pbs.twimg.com/profile_images/1089351499438804993/r8tlKeiD_normal.jpg","listed_count":2095,"profile_background_image_url":"http://abs.twimg.com/images/themes/theme1/bg.png","default_profile_image":false,"favourites_count":542,"description":"Some things are best left unexplained. Original account 8/21/13. Submissions/Business // @Scarpabiz","created_at":"Sun Aug 18 18:34:18 +0000 2013","is_translator":false,"profile_background_image_url_https":"https://abs.twimg.com/images/themes/theme1/bg.png","protected":false,"screen_name":"Unexplained","id_str":"1681324362","profile_link_color":"1DA1F2","translator_type":"none","id":1681324362,"geo_enabled":false,"profile_background_color":"C0DEED","lang":"en","profile_sidebar_border_color":"C0DEED","profile_text_color":"333333","verified":false,"profile_image_url":"http://pbs.twimg.com/profile_images/1089351499438804993/r8tlKeiD_normal.jpg","time_zone":null,"url":"http://Instagram.com/the.sketchfactor","contributors_enabled":false,"profile_background_tile":false,"profile_banner_url":"https://pbs.twimg.com/profile_banners/1681324362/1548556632","statuses_count":1692,"follow_request_sent":null,"followers_count":1105762,"profile_use_background_image":true,"default_profile":true,"following":null,"name":"The Unexplained","location":"Area 51","profile_sidebar_fill_color":"DDEEF6","notifications":null}},"in_reply_to_status_id_str":null,"in_reply_to_status_id":null,"created_at":"Tue Mar 12 20:34:33 +0000 2019","in_reply_to_user_id_str":null,"source":"<a href=\"http://twitter.com/download/android\" rel=\"nofollow\">Twitter for Android<\/a>","quoted_status_id":1104798247028224001,"retweet_count":0,"retweeted":false,"geo":null,"filter_level":"low","in_reply_to_screen_name":null,"is_quote_status":true,"id_str":"1105567777727877123","in_reply_to_user_id":null,"favorite_count":0,"id":1105567777727877123,"text":"Hostia, un Kabuto!","place":{"country_code":"ES","country":"España","full_name":"Madrid, España","bounding_box":{"coordinates":[[[-3.889005,40.312071],[-3.889005,40.643518],[-3.51801,40.643518],[-3.51801,40.312071]]],"type":"Polygon"},"place_type":"city","name":"Madrid","attributes":{},"id":"206c436ce43a43a3","url":"https://api.twitter.com/1.1/geo/id/206c436ce43a43a3.json"},"quoted_status_permalink":{"expanded":"https://twitter.com/Unexplained/status/1104798247028224001","display":"twitter.com/Unexplained/st\u2026","url":"https://t.co/vtlYVZjzfo"},"lang":"tl","quote_count":0,"favorited":false,"coordinates":null,"truncated":false,"timestamp_ms":"1552422873323","reply_count":0,"entities":{"urls":[],"hashtags":[],"user_mentions":[],"symbols":[]},"quoted_status_id_str":"1104798247028224001","contributors":null,"user":{"utc_offset":null,"friends_count":1040,"profile_image_url_https":"https://pbs.twimg.com/profile_images/1067542649060671488/_WT9VsFF_normal.jpg","listed_count":14,"profile_background_image_url":"http://abs.twimg.com/images/themes/theme9/bg.gif","default_profile_image":false,"favourites_count":13566,"description":"Soy un tipo con suerte que hace lo que le gusta.Deportista y Juerguista. Un auténtico superviviente. ♐♥Sagitario. \nMi risa es mi espada, y mi alegría mi escudo.","created_at":"Wed Nov 30 16:40:02 +0000 2011","is_translator":false,"profile_background_image_url_https":"https://abs.twimg.com/images/themes/theme9/bg.gif","protected":false,"screen_name":"franstronger8","id_str":"425152151","profile_link_color":"4584B5","translator_type":"regular","id":425152151,"geo_enabled":true,"profile_background_color":"8B542B","lang":"es","profile_sidebar_border_color":"000000","profile_text_color":"666666","verified":false,"profile_image_url":"http://pbs.twimg.com/profile_images/1067542649060671488/_WT9VsFF_normal.jpg","time_zone":null,"url":"https://www.instagram.com/franstronger8/","contributors_enabled":false,"profile_background_tile":true,"profile_banner_url":"https://pbs.twimg.com/profile_banners/425152151/1541307505","statuses_count":20786,"follow_request_sent":null,"followers_count":2786,"profile_use_background_image":true,"default_profile":false,"following":null,"name":"Fran Stronger","location":"Extremadura / Madrid (España)","profile_sidebar_fill_color":"252429","notifications":null}}