{"quoted_status":{"in_reply_to_status_id_str":null,"in_reply_to_status_id":null,"created_at":"Mon Mar 11 22:27:21 +0000 2019","in_reply_to_user_id_str":null,"source":"<a href=\"http://twitter.com/download/android\" rel=\"nofollow\">Twitter for Android<\/a>","quoted_status_id":1105164350078111744,"retweet_count":2357,"retweeted":false,"geo":null,"filter_level":"low","in_reply_to_screen_name":null,"is_quote_status":true,"id_str":"1105233776899248131","in_reply_to_user_id":null,"favorite_count":6682,"id":1105233776899248131,"text":"Dios qué goals pero estáis viendo cómo la mira??? por favor https://t.co/dSnagkOceZ","place":null,"lang":"es","quote_count":40,"favorited":false,"possibly_sensitive":false,"coordinates":null,"truncated":false,"reply_count":9,"entities":{"urls":[{"display_url":"twitter.com/desaferrada/st\u2026","indices":[60,83],"expanded_url":"https://twitter.com/desaferrada/status/1105164350078111744","url":"https://t.co/dSnagkOceZ"}],"hashtags":[],"user_mentions":[],"symbols":[]},"display_text_range":[0,59],"quoted_status_id_str":"1105164350078111744","contributors":null,"user":{"utc_offset":null,"friends_count":361,"profile_image_url_https":"https://pbs.twimg.com/profile_images/964584989496168448/9OY1lAa6_normal.jpg","listed_count":3,"profile_background_image_url":"","default_profile_image":false,"favourites_count":37020,"description":"No one\u2019s gonna take my soul away. | 💖💜💙","created_at":"Wed Feb 22 10:38:02 +0000 2017","is_translator":false,"profile_background_image_url_https":"","protected":false,"screen_name":"lauramizq","id_str":"834351536335646720","profile_link_color":"1DA1F2","translator_type":"none","id":834351536335646720,"geo_enabled":false,"profile_background_color":"F5F8FA","lang":"es","profile_sidebar_border_color":"C0DEED","profile_text_color":"333333","verified":false,"profile_image_url":"http://pbs.twimg.com/profile_images/964584989496168448/9OY1lAa6_normal.jpg","time_zone":null,"url":null,"contributors_enabled":false,"profile_background_tile":false,"profile_banner_url":"https://pbs.twimg.com/profile_banners/834351536335646720/1517959772","statuses_count":9140,"follow_request_sent":null,"followers_count":321,"profile_use_background_image":true,"default_profile":true,"following":null,"name":"Lau🌹","location":null,"profile_sidebar_fill_color":"DDEEF6","notifications":null}},"in_reply_to_status_id_str":null,"in_reply_to_status_id":null,"created_at":"Tue Mar 12 20:46:40 +0000 2019","in_reply_to_user_id_str":null,"source":"<a href=\"http://twitter.com/download/iphone\" rel=\"nofollow\">Twitter for iPhone<\/a>","quoted_status_id":1105233776899248131,"retweet_count":0,"retweeted":false,"geo":null,"filter_level":"low","in_reply_to_screen_name":null,"is_quote_status":true,"id_str":"1105570827771301889","in_reply_to_user_id":null,"favorite_count":0,"id":1105570827771301889,"text":"Es que😭","place":{"country_code":"ES","country":"España","full_name":"Madrid, España","bounding_box":{"coordinates":[[[-3.889005,40.312071],[-3.889005,40.643518],[-3.51801,40.643518],[-3.51801,40.312071]]],"type":"Polygon"},"place_type":"city","name":"Madrid","attributes":{},"id":"206c436ce43a43a3","url":"https://api.twitter.com/1.1/geo/id/206c436ce43a43a3.json"},"quoted_status_permalink":{"expanded":"https://twitter.com/lauramizq/status/1105233776899248131","display":"twitter.com/lauramizq/stat\u2026","url":"https://t.co/B1phTPO517"},"lang":"es","quote_count":0,"favorited":false,"coordinates":null,"truncated":false,"timestamp_ms":"1552423600510","reply_count":0,"entities":{"urls":[],"hashtags":[],"user_mentions":[],"symbols":[]},"quoted_status_id_str":"1105233776899248131","contributors":null,"user":{"utc_offset":null,"friends_count":1380,"profile_image_url_https":"https://pbs.twimg.com/profile_images/1025281942512721920/LgaYEelF_normal.jpg","listed_count":16,"profile_background_image_url":"http://abs.twimg.com/images/themes/theme1/bg.png","default_profile_image":false,"favourites_count":29619,"description":"Your art matters it's what got me here // Oye que ya he abrazado a all time low ahora que hago? amante del séptimo arte","created_at":"Mon Dec 03 18:59:04 +0000 2012","is_translator":false,"profile_background_image_url_https":"https://abs.twimg.com/images/themes/theme1/bg.png","protected":false,"screen_name":"Elenuus_ATL","id_str":"987222428","profile_link_color":"000000","translator_type":"regular","id":987222428,"geo_enabled":true,"profile_background_color":"DBE9ED","lang":"es","profile_sidebar_border_color":"000000","profile_text_color":"333333","verified":false,"profile_image_url":"http://pbs.twimg.com/profile_images/1025281942512721920/LgaYEelF_normal.jpg","time_zone":null,"url":"http://cinefilosplace.blogspot.com.es/","contributors_enabled":false,"profile_background_tile":true,"profile_banner_url":"https://pbs.twimg.com/profile_banners/987222428/1550602671","statuses_count":104087,"follow_request_sent":null,"followers_count":1517,"profile_use_background_image":true,"default_profile":false,"following":null,"name":"Rick","location":"París, Francia","profile_sidebar_fill_color":"DDEEF6","notifications":null}}