{"extended_tweet":{"entities":{"urls":[{"display_url":"instagram.com/p/Bu7BySklJ0p/\u2026","indices":[185,208],"expanded_url":"https://www.instagram.com/p/Bu7BySklJ0p/?utm_source=ig_twitter_share&igshid=153qrg1guaupr","url":"https://t.co/DIbf1KEYsz"}],"hashtags":[],"user_mentions":[],"symbols":[]},"full_text":"Este miércoles a las 17.30 horas, Raquel Sánchez Ortiz nos contará \"Lasaña la araña\" un cuento bilingüe español ingles que nos habla sobre el acoso escolar. Imprescindible inscripción\u2026 https://t.co/DIbf1KEYsz","display_text_range":[0,208]},"in_reply_to_status_id_str":null,"in_reply_to_status_id":null,"created_at":"Tue Mar 12 20:51:13 +0000 2019","in_reply_to_user_id_str":null,"source":"<a href=\"http://instagram.com\" rel=\"nofollow\">Instagram<\/a>","retweet_count":0,"retweeted":false,"geo":{"coordinates":[40.35873,-3.69754],"type":"Point"},"filter_level":"low","in_reply_to_screen_name":null,"is_quote_status":false,"id_str":"1105571973315391488","in_reply_to_user_id":null,"favorite_count":0,"id":1105571973315391488,"text":"Este miércoles a las 17.30 horas, Raquel Sánchez Ortiz nos contará \"Lasaña la araña\" un cuento bilingüe español ing\u2026 https://t.co/1GyawRFVfa","place":{"country_code":"ES","country":"España","full_name":"Madrid, España","bounding_box":{"coordinates":[[[-3.889005,40.312071],[-3.889005,40.643518],[-3.51801,40.643518],[-3.51801,40.312071]]],"type":"Polygon"},"place_type":"city","name":"Madrid","attributes":{},"id":"206c436ce43a43a3","url":"https://api.twitter.com/1.1/geo/id/206c436ce43a43a3.json"},"lang":"es","quote_count":0,"favorited":false,"possibly_sensitive":false,"coordinates":{"coordinates":[-3.69754,40.35873],"type":"Point"},"truncated":true,"timestamp_ms":"1552423873629","reply_count":0,"entities":{"urls":[{"display_url":"twitter.com/i/web/status/1\u2026","indices":[117,140],"expanded_url":"https://twitter.com/i/web/status/1105571973315391488","url":"https://t.co/1GyawRFVfa"}],"hashtags":[],"user_mentions":[],"symbols":[]},"contributors":null,"user":{"utc_offset":null,"friends_count":144,"profile_image_url_https":"https://pbs.twimg.com/profile_images/771732305362690048/wQhWPHOB_normal.jpg","listed_count":12,"profile_background_image_url":"","default_profile_image":false,"favourites_count":213,"description":"Librería infantil y juvenil en Ciudad de los Ángeles (Villaverde)","created_at":"Tue Aug 09 18:06:04 +0000 2016","is_translator":false,"profile_background_image_url_https":"","protected":false,"screen_name":"turuletras","id_str":"763073877153120256","profile_link_color":"1DA1F2","translator_type":"none","id":763073877153120256,"geo_enabled":true,"profile_background_color":"F5F8FA","lang":"es","profile_sidebar_border_color":"C0DEED","profile_text_color":"333333","verified":false,"profile_image_url":"http://pbs.twimg.com/profile_images/771732305362690048/wQhWPHOB_normal.jpg","time_zone":null,"url":"http://www.turuletras.com","contributors_enabled":false,"profile_background_tile":false,"profile_banner_url":"https://pbs.twimg.com/profile_banners/763073877153120256/1472830320","statuses_count":720,"follow_request_sent":null,"followers_count":298,"profile_use_background_image":true,"default_profile":true,"following":null,"name":"Librería Turuletras","location":"Manojo de Rosas 44 Local 7, Madrid","profile_sidebar_fill_color":"DDEEF6","notifications":null}}