{"in_reply_to_status_id_str":"1105141330135531520","in_reply_to_status_id":1105141330135531520,"created_at":"Wed Mar 13 15:03:52 +0000 2019","in_reply_to_user_id_str":"58747912","source":"<a href=\"http://twitter.com/download/iphone\" rel=\"nofollow\">Twitter for iPhone<\/a>","retweet_count":0,"retweeted":false,"geo":null,"filter_level":"low","in_reply_to_screen_name":"JVCom","is_quote_status":false,"id_str":"1105846945963220992","in_reply_to_user_id":58747912,"favorite_count":0,"id":1105846945963220992,"text":"@JVCom Nintendogs, GTA chinatown, sims naufragés","place":{"country_code":"FR","country":"France","full_name":"France","bounding_box":{"coordinates":[[[-5.141593,41.364659],[-5.141593,51.088771],[9.559831,51.088771],[9.559831,41.364659]]],"type":"Polygon"},"place_type":"country","name":"France","attributes":{},"id":"f3bfc7dcc928977f","url":"https://api.twitter.com/1.1/geo/id/f3bfc7dcc928977f.json"},"lang":"pt","quote_count":0,"favorited":false,"coordinates":null,"truncated":false,"timestamp_ms":"1552489432217","reply_count":0,"entities":{"urls":[],"hashtags":[],"user_mentions":[{"indices":[0,6],"screen_name":"JVCom","id_str":"58747912","name":"jeuxvideo.com : news jeux vidéo","id":58747912}],"symbols":[]},"display_text_range":[7,48],"contributors":null,"user":{"utc_offset":null,"friends_count":164,"profile_image_url_https":"https://pbs.twimg.com/profile_images/1088523418646052865/hKSoQJmS_normal.jpg","listed_count":0,"profile_background_image_url":"","default_profile_image":false,"favourites_count":1294,"description":"18 y.o N I 🌘 SUN ☀️       Snap : doriane.mercier     #JeunesseNoirPeuDEspoir","created_at":"Sun Oct 21 17:53:16 +0000 2018","is_translator":false,"profile_background_image_url_https":"","protected":false,"screen_name":"DMercier27","id_str":"1054068114848133121","profile_link_color":"1DA1F2","translator_type":"none","id":1054068114848133121,"geo_enabled":true,"profile_background_color":"F5F8FA","lang":"en","profile_sidebar_border_color":"C0DEED","profile_text_color":"333333","verified":false,"profile_image_url":"http://pbs.twimg.com/profile_images/1088523418646052865/hKSoQJmS_normal.jpg","time_zone":null,"url":"https://www.facebook.com/profile.php?id=100007106622837","contributors_enabled":false,"profile_background_tile":false,"profile_banner_url":"https://pbs.twimg.com/profile_banners/1054068114848133121/1552252852","statuses_count":379,"follow_request_sent":null,"followers_count":37,"profile_use_background_image":true,"default_profile":true,"following":null,"name":"D0R!4N3 🌸✨","location":"Abbeville, France","profile_sidebar_fill_color":"DDEEF6","notifications":null}}