{"extended_entities":{"media":[{"display_url":"pic.twitter.com/aFt0JEbRDB","indices":[76,99],"sizes":{"small":{"w":500,"h":276,"resize":"fit"},"large":{"w":500,"h":276,"resize":"fit"},"thumb":{"w":150,"h":150,"resize":"crop"},"medium":{"w":500,"h":276,"resize":"fit"}},"id_str":"1105902836393668608","expanded_url":"https://twitter.com/sanyerme/status/1105902839816179713/photo/1","media_url_https":"https://pbs.twimg.com/media/D1j0xTdXcAAG4f2.jpg","id":1105902836393668608,"type":"photo","media_url":"http://pbs.twimg.com/media/D1j0xTdXcAAG4f2.jpg","url":"https://t.co/aFt0JEbRDB"}]},"in_reply_to_status_id_str":"1105868442979237891","in_reply_to_status_id":1105868442979237891,"created_at":"Wed Mar 13 18:45:58 +0000 2019","in_reply_to_user_id_str":"13662772","source":"<a href=\"http://twitter.com/download/android\" rel=\"nofollow\">Twitter for Android<\/a>","retweet_count":0,"retweeted":false,"geo":null,"filter_level":"low","in_reply_to_screen_name":"sanyerme","is_quote_status":false,"id_str":"1105902839816179713","in_reply_to_user_id":13662772,"favorite_count":0,"id":1105902839816179713,"text":"@guardiacivil Esta es la soluci칩n al dise침o de rotondas de m치s de un carril https://t.co/aFt0JEbRDB","place":{"country_code":"ES","country":"Espa침a","full_name":"Madrid, Espa침a","bounding_box":{"coordinates":[[[-3.889005,40.312071],[-3.889005,40.643518],[-3.51801,40.643518],[-3.51801,40.312071]]],"type":"Polygon"},"place_type":"city","name":"Madrid","attributes":{},"id":"206c436ce43a43a3","url":"https://api.twitter.com/1.1/geo/id/206c436ce43a43a3.json"},"lang":"es","quote_count":0,"favorited":false,"possibly_sensitive":false,"coordinates":null,"truncated":false,"timestamp_ms":"1552502758350","reply_count":0,"entities":{"urls":[],"hashtags":[],"media":[{"display_url":"pic.twitter.com/aFt0JEbRDB","indices":[76,99],"sizes":{"small":{"w":500,"h":276,"resize":"fit"},"large":{"w":500,"h":276,"resize":"fit"},"thumb":{"w":150,"h":150,"resize":"crop"},"medium":{"w":500,"h":276,"resize":"fit"}},"id_str":"1105902836393668608","expanded_url":"https://twitter.com/sanyerme/status/1105902839816179713/photo/1","media_url_https":"https://pbs.twimg.com/media/D1j0xTdXcAAG4f2.jpg","id":1105902836393668608,"type":"photo","media_url":"http://pbs.twimg.com/media/D1j0xTdXcAAG4f2.jpg","url":"https://t.co/aFt0JEbRDB"}],"user_mentions":[{"indices":[0,13],"screen_name":"guardiacivil","id_str":"295608887","name":"Guardia Civil 游쀯릖","id":295608887}],"symbols":[]},"display_text_range":[14,75],"contributors":null,"user":{"utc_offset":null,"friends_count":666,"profile_image_url_https":"https://pbs.twimg.com/profile_images/1351148164/German_Carn__5_normal.JPG","listed_count":2,"profile_background_image_url":"http://abs.twimg.com/images/themes/theme1/bg.png","default_profile_image":false,"favourites_count":1869,"description":"Famoso Compositor de Himnos populares y creador polifac칠tico conocido por su sistema de aprendizaje ortogr치fico del espa침ol.","created_at":"Tue Feb 19 08:09:50 +0000 2008","is_translator":false,"profile_background_image_url_https":"https://abs.twimg.com/images/themes/theme1/bg.png","protected":false,"screen_name":"sanyerme","id_str":"13662772","profile_link_color":"1DA1F2","translator_type":"none","id":13662772,"geo_enabled":true,"profile_background_color":"C0DEED","lang":"es","profile_sidebar_border_color":"C0DEED","profile_text_color":"333333","verified":false,"profile_image_url":"http://pbs.twimg.com/profile_images/1351148164/German_Carn__5_normal.JPG","time_zone":null,"url":"http://sites.google.com/site/germancasaresalonso/","contributors_enabled":false,"profile_background_tile":false,"profile_banner_url":"https://pbs.twimg.com/profile_banners/13662772/1385742132","statuses_count":207,"follow_request_sent":null,"followers_count":120,"profile_use_background_image":true,"default_profile":true,"following":null,"name":"Germ치n Casares","location":"Madrid","profile_sidebar_fill_color":"DDEEF6","notifications":null}}