{"extended_tweet":{"entities":{"urls":[{"display_url":"instagram.com/p/Bu_8T_8BwXM/\u2026","indices":[175,198],"expanded_url":"https://www.instagram.com/p/Bu_8T_8BwXM/?utm_source=ig_twitter_share&igshid=1nn9ub6bw011p","url":"https://t.co/JBZXywO5qH"}],"hashtags":[{"indices":[133,139],"text":"ainek"},{"indices":[140,149],"text":"ainekink"},{"indices":[150,160],"text":"ainek2019"},{"indices":[161,173],"text":"ainekdesign"}],"user_mentions":[],"symbols":[]},"full_text":"✖️PEONÍA✖️\nHecho en cactus_tattoo_madrid \nDone in cactus_tattoo_madrid 🌵\n\u2022\n\u2022\n📲 WhatsApp: 658381167\n📩 ainek_artattoo@hotmail.com\n\u2022\n\u2022 \n#ainek #ainekink #ainek2019 #ainekdesign\u2026 https://t.co/JBZXywO5qH","display_text_range":[0,198]},"in_reply_to_status_id_str":null,"in_reply_to_status_id":null,"created_at":"Thu Mar 14 18:39:37 +0000 2019","in_reply_to_user_id_str":null,"source":"<a href=\"http://instagram.com\" rel=\"nofollow\">Instagram<\/a>","retweet_count":0,"retweeted":false,"geo":{"coordinates":[40.46727,-3.63972],"type":"Point"},"filter_level":"low","in_reply_to_screen_name":null,"is_quote_status":false,"id_str":"1106263629542899712","in_reply_to_user_id":null,"favorite_count":0,"id":1106263629542899712,"text":"✖️PEONÍA✖️\nHecho en cactus_tattoo_madrid \nDone in cactus_tattoo_madrid 🌵\n\u2022\n\u2022\n📲 WhatsApp: 658381167\n📩 ainek_artattoo\u2026 https://t.co/c3YafPnvJn","place":{"country_code":"ES","country":"España","full_name":"Madrid, España","bounding_box":{"coordinates":[[[-3.889005,40.312071],[-3.889005,40.643518],[-3.51801,40.643518],[-3.51801,40.312071]]],"type":"Polygon"},"place_type":"city","name":"Madrid","attributes":{},"id":"206c436ce43a43a3","url":"https://api.twitter.com/1.1/geo/id/206c436ce43a43a3.json"},"lang":"en","quote_count":0,"favorited":false,"possibly_sensitive":false,"coordinates":{"coordinates":[-3.63972,40.46727],"type":"Point"},"truncated":true,"timestamp_ms":"1552588777324","reply_count":0,"entities":{"urls":[{"display_url":"twitter.com/i/web/status/1\u2026","indices":[117,140],"expanded_url":"https://twitter.com/i/web/status/1106263629542899712","url":"https://t.co/c3YafPnvJn"}],"hashtags":[],"user_mentions":[],"symbols":[]},"contributors":null,"user":{"utc_offset":null,"friends_count":103,"profile_image_url_https":"https://pbs.twimg.com/profile_images/1055427745176604672/ERsJ7-TI_normal.jpg","listed_count":0,"profile_background_image_url":"http://abs.twimg.com/images/themes/theme14/bg.gif","default_profile_image":false,"favourites_count":4083,"description":"INSTAGRAM: @ainek_artattoo","created_at":"Mon Jan 16 13:41:06 +0000 2012","is_translator":false,"profile_background_image_url_https":"https://abs.twimg.com/images/themes/theme14/bg.gif","protected":false,"screen_name":"LMontero_5","id_str":"465550356","profile_link_color":"009999","translator_type":"none","id":465550356,"geo_enabled":true,"profile_background_color":"131516","lang":"es","profile_sidebar_border_color":"EEEEEE","profile_text_color":"333333","verified":false,"profile_image_url":"http://pbs.twimg.com/profile_images/1055427745176604672/ERsJ7-TI_normal.jpg","time_zone":null,"url":null,"contributors_enabled":false,"profile_background_tile":true,"profile_banner_url":"https://pbs.twimg.com/profile_banners/465550356/1524518914","statuses_count":4819,"follow_request_sent":null,"followers_count":179,"profile_use_background_image":true,"default_profile":false,"following":null,"name":"Lau 🌿","location":"Madrid, Comunidad de Madrid","profile_sidebar_fill_color":"EFEFEF","notifications":null}}