{"in_reply_to_status_id_str":null,"in_reply_to_status_id":null,"created_at":"Thu Mar 14 17:58:32 +0000 2019","in_reply_to_user_id_str":null,"source":"<a href=\"https://dlvrit.com/\" rel=\"nofollow\">dlvr.it<\/a>","retweet_count":0,"retweeted":false,"geo":{"coordinates":[40.41976938,-3.75732422],"type":"Point"},"filter_level":"low","in_reply_to_screen_name":null,"is_quote_status":false,"id_str":"1106253292949008386","in_reply_to_user_id":null,"favorite_count":0,"id":1106253292949008386,"text":"ES-DESK \u2014 10 curiosidades de \"Will and Grace\" que debes saber https://t.co/0Y0gmapq97","place":{"country_code":"ES","country":"España","full_name":"Madrid, España","bounding_box":{"coordinates":[[[-3.889005,40.312071],[-3.889005,40.643518],[-3.51801,40.643518],[-3.51801,40.312071]]],"type":"Polygon"},"place_type":"city","name":"Madrid","attributes":{},"id":"206c436ce43a43a3","url":"https://api.twitter.com/1.1/geo/id/206c436ce43a43a3.json"},"lang":"es","quote_count":0,"favorited":false,"possibly_sensitive":false,"coordinates":{"coordinates":[-3.75732422,40.41976938],"type":"Point"},"truncated":false,"timestamp_ms":"1552586312888","reply_count":0,"entities":{"urls":[{"display_url":"dlvr.it/R0qzK8","indices":[62,85],"expanded_url":"http://dlvr.it/R0qzK8","url":"https://t.co/0Y0gmapq97"}],"hashtags":[],"user_mentions":[],"symbols":[]},"contributors":null,"user":{"utc_offset":null,"friends_count":954,"profile_image_url_https":"https://pbs.twimg.com/profile_images/378800000775162762/01180740df38e66ce70a9d7c6ee7c312_normal.png","listed_count":167,"profile_background_image_url":"http://abs.twimg.com/images/themes/theme1/bg.png","default_profile_image":false,"favourites_count":0,"description":"Español - Português | Keeping up-to-date on global social exclusion \u2014 Stigmabase is a Canadian Nonprofit Initiative | F in 2010","created_at":"Fri Sep 03 15:34:08 +0000 2010","is_translator":false,"profile_background_image_url_https":"https://abs.twimg.com/images/themes/theme1/bg.png","protected":false,"screen_name":"PairsonnalitesE","id_str":"186478529","profile_link_color":"0084B4","translator_type":"none","id":186478529,"geo_enabled":true,"profile_background_color":"FFFFFF","lang":"es","profile_sidebar_border_color":"FFFFFF","profile_text_color":"333333","verified":false,"profile_image_url":"http://pbs.twimg.com/profile_images/378800000775162762/01180740df38e66ce70a9d7c6ee7c312_normal.png","time_zone":null,"url":"http://es.stigmabase.org","contributors_enabled":false,"profile_background_tile":false,"profile_banner_url":"https://pbs.twimg.com/profile_banners/186478529/1385143410","statuses_count":823503,"follow_request_sent":null,"followers_count":2034,"profile_use_background_image":true,"default_profile":false,"following":null,"name":"Stigmabase | ES","location":"Las Américas | España","profile_sidebar_fill_color":"EFEFEF","notifications":null}}