<?xml version='1.0' encoding='UTF-8'?>
<GateDocument version="3">
<!-- The document's features-->

<GateDocumentFeatures>
<Feature>
  <Name className="java.lang.String">gate.SourceURL</Name>
  <Value className="java.lang.String">file:/C:/Users/Gary%20Ulloa/Documents/NetBeansProjects/AIW2019_P3_G9/data/json/1106260472465145857.json</Value>
</Feature>
<Feature>
  <Name className="java.lang.String">lang</Name>
  <Value className="java.lang.String">english</Value>
</Feature>
<Feature>
  <Name className="java.lang.String">MimeType</Name>
  <Value className="java.lang.String">text/x-json-twitter</Value>
</Feature>
<Feature>
  <Name className="java.lang.String">docNewLineType</Name>
  <Value className="java.lang.String"></Value>
</Feature>
</GateDocumentFeatures>
<!-- The document content area with serialized nodes -->

<TextWithNodes><Node id="0"/>Read<Node id="4"/> <Node id="5"/>and<Node id="8"/> <Node id="9"/>think<Node id="14"/>.<Node id="15"/>.<Node id="16"/>.<Node id="17"/>this<Node id="21"/> <Node id="22"/>is<Node id="24"/> <Node id="25"/>mean<Node id="29"/> <Node id="30"/>of<Node id="32"/> <Node id="33"/>being<Node id="38"/> <Node id="39"/>a<Node id="40"/> <Node id="41"/>DBA<Node id="44"/>.<Node id="45"/>
<Node id="46"/>
<Node id="47"/></TextWithNodes>
<!-- The default annotation set -->

<AnnotationSet>
<Annotation Id="0" Type="Tweet" StartNode="0" EndNode="45">
<Feature>
  <Name className="java.lang.String">quoted_status</Name>
  <Value className="gate.corpora.ObjectWrapper"><![CDATA[<?xml version='1.0' encoding='UTF-8'?><gate.corpora.ObjectWrapper><value class="gate.util.SimpleFeatureMapImpl" serialization="custom"><gate.util.SimpleMapImpl><default><capacity>48</capacity><count>31</count><theKeys><string>extended_tweet</string><string>in_reply_to_status_id_str</string><string>in_reply_to_status_id</string><string>created_at</string><string>in_reply_to_user_id_str</string><string>source</string><string>quoted_status_id</string><string>retweet_count</string><string>retweeted</string><string>geo</string><string>filter_level</string><string>in_reply_to_screen_name</string><string>is_quote_status</string><string>id_str</string><string>in_reply_to_user_id</string><string>favorite_count</string><string>id</string><string>text</string><string>place</string><string>lang</string><string>quote_count</string><string>favorited</string><string>possibly_sensitive</string><string>coordinates</string><string>truncated</string><string>reply_count</string><string>entities</string><string>display_text_range</string><string>quoted_status_id_str</string><string>contributors</string><string>user</string><null/><null/><null/><null/><null/><null/><null/><null/><null/><null/><null/><null/><null/><null/><null/><null/><null/></theKeys><theValues><gate.util.SimpleFeatureMapImpl serialization="custom"><gate.util.SimpleMapImpl><default><capacity>3</capacity><count>3</count><theKeys><string>entities</string><string>full_text</string><string>display_text_range</string></theKeys><theValues><gate.util.SimpleFeatureMapImpl serialization="custom"><gate.util.SimpleMapImpl><default><capacity>6</capacity><count>4</count><theKeys><string>urls</string><string>hashtags</string><string>user_mentions</string><string>symbols</string><null/><null/></theKeys><theValues><list><gate.util.SimpleFeatureMapImpl serialization="custom"><gate.util.SimpleMapImpl><default><capacity>6</capacity><count>4</count><theKeys><string>display_url</string><string>indices</string><string>expanded_url</string><string>url</string><null/><null/></theKeys><theValues><string>twitter.com/jericon/status…</string><list><int>284</int><int>307</int></list><string>https://twitter.com/jericon/status/1105875153831878657</string><string>https://t.co/WUd6Cmw6yn</string><null/><null/></theValues></default></gate.util.SimpleMapImpl></gate.util.SimpleFeatureMapImpl></list><list/><list/><list/><null/><null/></theValues></default></gate.util.SimpleMapImpl></gate.util.SimpleFeatureMapImpl><string>This conversation between ex-Twitter-DBAs is why I love and respect DBAs. Scroll to the top and read down the replies. Then, click on Lisa’s original tweet at the top and read the _other_ replies. If you underestimate or disrespect the people who keep your data safe &amp;amp; available… https://t.co/WUd6Cmw6yn</string><list><int>0</int><int>283</int></list></theValues></default></gate.util.SimpleMapImpl></gate.util.SimpleFeatureMapImpl><null/><null/><string>Thu Mar 14 15:05:11 +0000 2019</string><null/><string>&lt;a href="https://tapbots.com/software/tweetbot/mac" rel="nofollow">Tweetbot for Mac&lt;/a></string><string>1105875153831878657</string><int>17</int><boolean>false</boolean><null/><string>low</string><null/><boolean>true</boolean><string>1106209667187912706</string><null/><int>52</int><string>1106209667187912706</string><string>This conversation between ex-Twitter-DBAs is why I love and respect DBAs. Scroll to the top and read down the repli… https://t.co/ayoj378R6A</string><null/><string>en</string><int>1</int><boolean>false</boolean><boolean>false</boolean><null/><boolean>true</boolean><int>4</int><gate.util.SimpleFeatureMapImpl serialization="custom"><gate.util.SimpleMapImpl><default><capacity>6</capacity><count>4</count><theKeys><string>urls</string><string>hashtags</string><string>user_mentions</string><string>symbols</string><null/><null/></theKeys><theValues><list><gate.util.SimpleFeatureMapImpl serialization="custom"><gate.util.SimpleMapImpl><default><capacity>6</capacity><count>4</count><theKeys><string>display_url</string><string>indices</string><string>expanded_url</string><string>url</string><null/><null/></theKeys><theValues><string>twitter.com/i/web/status/1…</string><list><int>117</int><int>140</int></list><string>https://twitter.com/i/web/status/1106209667187912706</string><string>https://t.co/ayoj378R6A</string><null/><null/></theValues></default></gate.util.SimpleMapImpl></gate.util.SimpleFeatureMapImpl></list><list/><list/><list/><null/><null/></theValues></default></gate.util.SimpleMapImpl></gate.util.SimpleFeatureMapImpl><list><int>0</int><int>140</int></list><string>1105875153831878657</string><null/><gate.util.SimpleFeatureMapImpl serialization="custom"><gate.util.SimpleMapImpl><default><capacity>48</capacity><count>39</count><theKeys><string>utc_offset</string><string>friends_count</string><string>profile_image_url_https</string><string>listed_count</string><string>profile_background_image_url</string><string>default_profile_image</string><string>favourites_count</string><string>description</string><string>created_at</string><string>is_translator</string><string>profile_background_image_url_https</string><string>protected</string><string>screen_name</string><string>id_str</string><string>profile_link_color</string><string>translator_type</string><string>id</string><string>geo_enabled</string><string>profile_background_color</string><string>lang</string><string>profile_sidebar_border_color</string><string>profile_text_color</string><string>verified</string><string>profile_image_url</string><string>time_zone</string><string>url</string><string>contributors_enabled</string><string>profile_background_tile</string><string>profile_banner_url</string><string>statuses_count</string><string>follow_request_sent</string><string>followers_count</string><string>profile_use_background_image</string><string>default_profile</string><string>following</string><string>name</string><string>location</string><string>profile_sidebar_fill_color</string><string>notifications</string><null/><null/><null/><null/><null/><null/><null/><null/><null/></theKeys><theValues><null/><int>103</int><string>https://pbs.twimg.com/profile_images/1062705123225411584/uRheCEkM_normal.jpg</string><int>398</int><string>http://abs.twimg.com/images/themes/theme15/bg.png</string><boolean>false</boolean><int>27</int><string>CTO @VividCortex. Working on personal growth &amp; making a difference. Silence is violence, but a little learning is a dangerous thing. He/him.</string><string>Thu Apr 02 12:08:55 +0000 2009</string><boolean>false</boolean><string>https://abs.twimg.com/images/themes/theme15/bg.png</string><boolean>false</boolean><string>xaprb</string><string>28325059</string><string>0084B4</string><string>none</string><int>28325059</int><boolean>false</boolean><string>022330</string><string>en</string><string>A8C7F7</string><string>333333</string><boolean>true</boolean><string>http://pbs.twimg.com/profile_images/1062705123225411584/uRheCEkM_normal.jpg</string><null/><string>https://www.vividcortex.com</string><boolean>false</boolean><boolean>false</boolean><string>https://pbs.twimg.com/profile_banners/28325059/1552317159</string><int>845</int><null/><int>8547</int><boolean>true</boolean><boolean>false</boolean><null/><string>Baron Sc​hwartz</string><string>Here, now</string><string>C0DFEC</string><null/><null/><null/><null/><null/><null/><null/><null/><null/><null/></theValues></default></gate.util.SimpleMapImpl></gate.util.SimpleFeatureMapImpl><null/><null/><null/><null/><null/><null/><null/><null/><null/><null/><null/><null/><null/><null/><null/><null/><null/></theValues></default></gate.util.SimpleMapImpl></value></gate.corpora.ObjectWrapper>]]></Value>
</Feature>
<Feature>
  <Name className="java.lang.String">created_at</Name>
  <Value className="java.lang.String">Thu Mar 14 18:27:04 +0000 2019</Value>
</Feature>
<Feature>
  <Name className="java.lang.String">source</Name>
  <Value className="java.lang.String">&lt;a href="http://twitter.com/download/android" rel="nofollow">Twitter for Android&lt;/a></Value>
</Feature>
<Feature>
  <Name className="java.lang.String">quoted_status_id</Name>
  <Value className="java.lang.String">1106209667187912706</Value>
</Feature>
<Feature>
  <Name className="java.lang.String">retweet_count</Name>
  <Value className="java.lang.Integer">0</Value>
</Feature>
<Feature>
  <Name className="java.lang.String">retweeted</Name>
  <Value className="java.lang.Boolean">false</Value>
</Feature>
<Feature>
  <Name className="java.lang.String">filter_level</Name>
  <Value className="java.lang.String">low</Value>
</Feature>
<Feature>
  <Name className="java.lang.String">is_quote_status</Name>
  <Value className="java.lang.Boolean">true</Value>
</Feature>
<Feature>
  <Name className="java.lang.String">id_str</Name>
  <Value className="java.lang.String">1106260472465145857</Value>
</Feature>
<Feature>
  <Name className="java.lang.String">favorite_count</Name>
  <Value className="java.lang.Integer">0</Value>
</Feature>
<Feature>
  <Name className="java.lang.String">id</Name>
  <Value className="java.lang.String">1106260472465145857</Value>
</Feature>
<Feature>
  <Name className="java.lang.String">place</Name>
  <Value className="gate.corpora.ObjectWrapper"><![CDATA[<?xml version='1.0' encoding='UTF-8'?><gate.corpora.ObjectWrapper><value class="gate.util.SimpleFeatureMapImpl" serialization="custom"><gate.util.SimpleMapImpl><default><capacity>12</capacity><count>9</count><theKeys><string>country_code</string><string>country</string><string>full_name</string><string>bounding_box</string><string>place_type</string><string>name</string><string>attributes</string><string>id</string><string>url</string><null/><null/><null/></theKeys><theValues><string>ES</string><string>España</string><string>Madrid, España</string><gate.util.SimpleFeatureMapImpl serialization="custom"><gate.util.SimpleMapImpl><default><capacity>3</capacity><count>2</count><theKeys><string>coordinates</string><string>type</string><null/></theKeys><theValues><list><list><list><double>-3.889005</double><double>40.312071</double></list><list><double>-3.889005</double><double>40.643518</double></list><list><double>-3.51801</double><double>40.643518</double></list><list><double>-3.51801</double><double>40.312071</double></list></list></list><string>Polygon</string><null/></theValues></default></gate.util.SimpleMapImpl></gate.util.SimpleFeatureMapImpl><string>city</string><string>Madrid</string><gate.util.SimpleFeatureMapImpl serialization="custom"><gate.util.SimpleMapImpl><default><capacity>3</capacity><count>0</count><theKeys><null/><null/><null/></theKeys><theValues><null/><null/><null/></theValues></default></gate.util.SimpleMapImpl></gate.util.SimpleFeatureMapImpl><string>206c436ce43a43a3</string><string>https://api.twitter.com/1.1/geo/id/206c436ce43a43a3.json</string><null/><null/><null/></theValues></default></gate.util.SimpleMapImpl></value></gate.corpora.ObjectWrapper>]]></Value>
</Feature>
<Feature>
  <Name className="java.lang.String">quoted_status_permalink</Name>
  <Value className="gate.corpora.ObjectWrapper"><![CDATA[<?xml version='1.0' encoding='UTF-8'?><gate.corpora.ObjectWrapper><value class="gate.util.SimpleFeatureMapImpl" serialization="custom"><gate.util.SimpleMapImpl><default><capacity>3</capacity><count>3</count><theKeys><string>expanded</string><string>display</string><string>url</string></theKeys><theValues><string>https://twitter.com/xaprb/status/1106209667187912706</string><string>twitter.com/xaprb/status/1…</string><string>https://t.co/9Ibhv2V1r4</string></theValues></default></gate.util.SimpleMapImpl></value></gate.corpora.ObjectWrapper>]]></Value>
</Feature>
<Feature>
  <Name className="java.lang.String">lang</Name>
  <Value className="java.lang.String">en</Value>
</Feature>
<Feature>
  <Name className="java.lang.String">quote_count</Name>
  <Value className="java.lang.Integer">0</Value>
</Feature>
<Feature>
  <Name className="java.lang.String">favorited</Name>
  <Value className="java.lang.Boolean">false</Value>
</Feature>
<Feature>
  <Name className="java.lang.String">truncated</Name>
  <Value className="java.lang.Boolean">false</Value>
</Feature>
<Feature>
  <Name className="java.lang.String">timestamp_ms</Name>
  <Value className="java.lang.String">1552588024618</Value>
</Feature>
<Feature>
  <Name className="java.lang.String">reply_count</Name>
  <Value className="java.lang.Integer">0</Value>
</Feature>
<Feature>
  <Name className="java.lang.String">entities</Name>
  <Value className="gate.corpora.ObjectWrapper"><![CDATA[<?xml version='1.0' encoding='UTF-8'?><gate.corpora.ObjectWrapper><value class="gate.util.SimpleFeatureMapImpl" serialization="custom"><gate.util.SimpleMapImpl><default><capacity>6</capacity><count>4</count><theKeys><string>urls</string><string>hashtags</string><string>user_mentions</string><string>symbols</string><null/><null/></theKeys><theValues><list/><list/><list/><list/><null/><null/></theValues></default></gate.util.SimpleMapImpl></value></gate.corpora.ObjectWrapper>]]></Value>
</Feature>
<Feature>
  <Name className="java.lang.String">quoted_status_id_str</Name>
  <Value className="java.lang.String">1106209667187912706</Value>
</Feature>
<Feature>
  <Name className="java.lang.String">user</Name>
  <Value className="gate.corpora.ObjectWrapper"><![CDATA[<?xml version='1.0' encoding='UTF-8'?><gate.corpora.ObjectWrapper><value class="gate.util.SimpleFeatureMapImpl" serialization="custom"><gate.util.SimpleMapImpl><default><capacity>48</capacity><count>39</count><theKeys><string>utc_offset</string><string>friends_count</string><string>profile_image_url_https</string><string>listed_count</string><string>profile_background_image_url</string><string>default_profile_image</string><string>favourites_count</string><string>description</string><string>created_at</string><string>is_translator</string><string>profile_background_image_url_https</string><string>protected</string><string>screen_name</string><string>id_str</string><string>profile_link_color</string><string>translator_type</string><string>id</string><string>geo_enabled</string><string>profile_background_color</string><string>lang</string><string>profile_sidebar_border_color</string><string>profile_text_color</string><string>verified</string><string>profile_image_url</string><string>time_zone</string><string>url</string><string>contributors_enabled</string><string>profile_background_tile</string><string>profile_banner_url</string><string>statuses_count</string><string>follow_request_sent</string><string>followers_count</string><string>profile_use_background_image</string><string>default_profile</string><string>following</string><string>name</string><string>location</string><string>profile_sidebar_fill_color</string><string>notifications</string><null/><null/><null/><null/><null/><null/><null/><null/><null/></theKeys><theValues><null/><int>241</int><string>https://pbs.twimg.com/profile_images/867991061146161152/pb6jmRGY_normal.jpg</string><int>3</int><string>http://abs.twimg.com/images/themes/theme1/bg.png</string><boolean>false</boolean><int>6942</int><string>I run for something better. Data Engineer MySQL based systems, NoSQL or any DB to be managed</string><string>Sat Feb 09 11:46:03 +0000 2008</string><boolean>false</boolean><string>https://abs.twimg.com/images/themes/theme1/bg.png</string><boolean>false</boolean><string>rmateos</string><string>13279322</string><string>87B6E8</string><string>none</string><int>13279322</int><boolean>true</boolean><string>F5F5F5</string><string>es</string><string>FFFFFF</string><string>333333</string><boolean>false</boolean><string>http://pbs.twimg.com/profile_images/867991061146161152/pb6jmRGY_normal.jpg</string><null/><null/><boolean>false</boolean><boolean>false</boolean><string>https://pbs.twimg.com/profile_banners/13279322/1469139154</string><int>8664</int><null/><int>95</int><boolean>true</boolean><boolean>false</boolean><null/><string>rmateos</string><string>Madrid</string><string>DDEEF6</string><null/><null/><null/><null/><null/><null/><null/><null/><null/><null/></theValues></default></gate.util.SimpleMapImpl></value></gate.corpora.ObjectWrapper>]]></Value>
</Feature>
</Annotation>
<Annotation Id="1" Type="Token" StartNode="0" EndNode="4">
<Feature>
  <Name className="java.lang.String">length</Name>
  <Value className="java.lang.String">4</Value>
</Feature>
<Feature>
  <Name className="java.lang.String">orth</Name>
  <Value className="java.lang.String">upperInitial</Value>
</Feature>
<Feature>
  <Name className="java.lang.String">string</Name>
  <Value className="java.lang.String">Read</Value>
</Feature>
<Feature>
  <Name className="java.lang.String">category</Name>
  <Value className="java.lang.String">VB</Value>
</Feature>
<Feature>
  <Name className="java.lang.String">kind</Name>
  <Value className="java.lang.String">word</Value>
</Feature>
</Annotation>
<Annotation Id="2" Type="SpaceToken" StartNode="4" EndNode="5">
<Feature>
  <Name className="java.lang.String">string</Name>
  <Value className="java.lang.String"> </Value>
</Feature>
<Feature>
  <Name className="java.lang.String">length</Name>
  <Value className="java.lang.String">1</Value>
</Feature>
<Feature>
  <Name className="java.lang.String">kind</Name>
  <Value className="java.lang.String">space</Value>
</Feature>
</Annotation>
<Annotation Id="3" Type="Token" StartNode="5" EndNode="8">
<Feature>
  <Name className="java.lang.String">length</Name>
  <Value className="java.lang.String">3</Value>
</Feature>
<Feature>
  <Name className="java.lang.String">orth</Name>
  <Value className="java.lang.String">lowercase</Value>
</Feature>
<Feature>
  <Name className="java.lang.String">string</Name>
  <Value className="java.lang.String">and</Value>
</Feature>
<Feature>
  <Name className="java.lang.String">category</Name>
  <Value className="java.lang.String">CC</Value>
</Feature>
<Feature>
  <Name className="java.lang.String">kind</Name>
  <Value className="java.lang.String">word</Value>
</Feature>
</Annotation>
<Annotation Id="4" Type="SpaceToken" StartNode="8" EndNode="9">
<Feature>
  <Name className="java.lang.String">string</Name>
  <Value className="java.lang.String"> </Value>
</Feature>
<Feature>
  <Name className="java.lang.String">length</Name>
  <Value className="java.lang.String">1</Value>
</Feature>
<Feature>
  <Name className="java.lang.String">kind</Name>
  <Value className="java.lang.String">space</Value>
</Feature>
</Annotation>
<Annotation Id="5" Type="Token" StartNode="9" EndNode="14">
<Feature>
  <Name className="java.lang.String">length</Name>
  <Value className="java.lang.String">5</Value>
</Feature>
<Feature>
  <Name className="java.lang.String">orth</Name>
  <Value className="java.lang.String">lowercase</Value>
</Feature>
<Feature>
  <Name className="java.lang.String">string</Name>
  <Value className="java.lang.String">think</Value>
</Feature>
<Feature>
  <Name className="java.lang.String">category</Name>
  <Value className="java.lang.String">VB</Value>
</Feature>
<Feature>
  <Name className="java.lang.String">kind</Name>
  <Value className="java.lang.String">word</Value>
</Feature>
</Annotation>
<Annotation Id="6" Type="Token" StartNode="14" EndNode="15">
<Feature>
  <Name className="java.lang.String">length</Name>
  <Value className="java.lang.String">1</Value>
</Feature>
<Feature>
  <Name className="java.lang.String">string</Name>
  <Value className="java.lang.String">.</Value>
</Feature>
<Feature>
  <Name className="java.lang.String">category</Name>
  <Value className="java.lang.String">.</Value>
</Feature>
<Feature>
  <Name className="java.lang.String">kind</Name>
  <Value className="java.lang.String">punctuation</Value>
</Feature>
</Annotation>
<Annotation Id="7" Type="Token" StartNode="15" EndNode="16">
<Feature>
  <Name className="java.lang.String">length</Name>
  <Value className="java.lang.String">1</Value>
</Feature>
<Feature>
  <Name className="java.lang.String">string</Name>
  <Value className="java.lang.String">.</Value>
</Feature>
<Feature>
  <Name className="java.lang.String">category</Name>
  <Value className="java.lang.String">UH</Value>
</Feature>
<Feature>
  <Name className="java.lang.String">kind</Name>
  <Value className="java.lang.String">punctuation</Value>
</Feature>
</Annotation>
<Annotation Id="8" Type="Token" StartNode="16" EndNode="17">
<Feature>
  <Name className="java.lang.String">length</Name>
  <Value className="java.lang.String">1</Value>
</Feature>
<Feature>
  <Name className="java.lang.String">string</Name>
  <Value className="java.lang.String">.</Value>
</Feature>
<Feature>
  <Name className="java.lang.String">category</Name>
  <Value className="java.lang.String">.</Value>
</Feature>
<Feature>
  <Name className="java.lang.String">kind</Name>
  <Value className="java.lang.String">punctuation</Value>
</Feature>
</Annotation>
<Annotation Id="9" Type="Token" StartNode="17" EndNode="21">
<Feature>
  <Name className="java.lang.String">length</Name>
  <Value className="java.lang.String">4</Value>
</Feature>
<Feature>
  <Name className="java.lang.String">orth</Name>
  <Value className="java.lang.String">lowercase</Value>
</Feature>
<Feature>
  <Name className="java.lang.String">string</Name>
  <Value className="java.lang.String">this</Value>
</Feature>
<Feature>
  <Name className="java.lang.String">category</Name>
  <Value className="java.lang.String">DT</Value>
</Feature>
<Feature>
  <Name className="java.lang.String">kind</Name>
  <Value className="java.lang.String">word</Value>
</Feature>
</Annotation>
<Annotation Id="10" Type="SpaceToken" StartNode="21" EndNode="22">
<Feature>
  <Name className="java.lang.String">string</Name>
  <Value className="java.lang.String"> </Value>
</Feature>
<Feature>
  <Name className="java.lang.String">length</Name>
  <Value className="java.lang.String">1</Value>
</Feature>
<Feature>
  <Name className="java.lang.String">kind</Name>
  <Value className="java.lang.String">space</Value>
</Feature>
</Annotation>
<Annotation Id="11" Type="Token" StartNode="22" EndNode="24">
<Feature>
  <Name className="java.lang.String">length</Name>
  <Value className="java.lang.String">2</Value>
</Feature>
<Feature>
  <Name className="java.lang.String">orth</Name>
  <Value className="java.lang.String">lowercase</Value>
</Feature>
<Feature>
  <Name className="java.lang.String">string</Name>
  <Value className="java.lang.String">is</Value>
</Feature>
<Feature>
  <Name className="java.lang.String">category</Name>
  <Value className="java.lang.String">VBZ</Value>
</Feature>
<Feature>
  <Name className="java.lang.String">kind</Name>
  <Value className="java.lang.String">word</Value>
</Feature>
</Annotation>
<Annotation Id="12" Type="SpaceToken" StartNode="24" EndNode="25">
<Feature>
  <Name className="java.lang.String">string</Name>
  <Value className="java.lang.String"> </Value>
</Feature>
<Feature>
  <Name className="java.lang.String">length</Name>
  <Value className="java.lang.String">1</Value>
</Feature>
<Feature>
  <Name className="java.lang.String">kind</Name>
  <Value className="java.lang.String">space</Value>
</Feature>
</Annotation>
<Annotation Id="13" Type="Token" StartNode="25" EndNode="29">
<Feature>
  <Name className="java.lang.String">length</Name>
  <Value className="java.lang.String">4</Value>
</Feature>
<Feature>
  <Name className="java.lang.String">orth</Name>
  <Value className="java.lang.String">lowercase</Value>
</Feature>
<Feature>
  <Name className="java.lang.String">string</Name>
  <Value className="java.lang.String">mean</Value>
</Feature>
<Feature>
  <Name className="java.lang.String">category</Name>
  <Value className="java.lang.String">JJ</Value>
</Feature>
<Feature>
  <Name className="java.lang.String">kind</Name>
  <Value className="java.lang.String">word</Value>
</Feature>
</Annotation>
<Annotation Id="14" Type="SpaceToken" StartNode="29" EndNode="30">
<Feature>
  <Name className="java.lang.String">string</Name>
  <Value className="java.lang.String"> </Value>
</Feature>
<Feature>
  <Name className="java.lang.String">length</Name>
  <Value className="java.lang.String">1</Value>
</Feature>
<Feature>
  <Name className="java.lang.String">kind</Name>
  <Value className="java.lang.String">space</Value>
</Feature>
</Annotation>
<Annotation Id="15" Type="Token" StartNode="30" EndNode="32">
<Feature>
  <Name className="java.lang.String">length</Name>
  <Value className="java.lang.String">2</Value>
</Feature>
<Feature>
  <Name className="java.lang.String">orth</Name>
  <Value className="java.lang.String">lowercase</Value>
</Feature>
<Feature>
  <Name className="java.lang.String">string</Name>
  <Value className="java.lang.String">of</Value>
</Feature>
<Feature>
  <Name className="java.lang.String">category</Name>
  <Value className="java.lang.String">IN</Value>
</Feature>
<Feature>
  <Name className="java.lang.String">kind</Name>
  <Value className="java.lang.String">word</Value>
</Feature>
</Annotation>
<Annotation Id="16" Type="SpaceToken" StartNode="32" EndNode="33">
<Feature>
  <Name className="java.lang.String">string</Name>
  <Value className="java.lang.String"> </Value>
</Feature>
<Feature>
  <Name className="java.lang.String">length</Name>
  <Value className="java.lang.String">1</Value>
</Feature>
<Feature>
  <Name className="java.lang.String">kind</Name>
  <Value className="java.lang.String">space</Value>
</Feature>
</Annotation>
<Annotation Id="17" Type="Token" StartNode="33" EndNode="38">
<Feature>
  <Name className="java.lang.String">length</Name>
  <Value className="java.lang.String">5</Value>
</Feature>
<Feature>
  <Name className="java.lang.String">orth</Name>
  <Value className="java.lang.String">lowercase</Value>
</Feature>
<Feature>
  <Name className="java.lang.String">string</Name>
  <Value className="java.lang.String">being</Value>
</Feature>
<Feature>
  <Name className="java.lang.String">category</Name>
  <Value className="java.lang.String">VBG</Value>
</Feature>
<Feature>
  <Name className="java.lang.String">kind</Name>
  <Value className="java.lang.String">word</Value>
</Feature>
</Annotation>
<Annotation Id="18" Type="SpaceToken" StartNode="38" EndNode="39">
<Feature>
  <Name className="java.lang.String">string</Name>
  <Value className="java.lang.String"> </Value>
</Feature>
<Feature>
  <Name className="java.lang.String">length</Name>
  <Value className="java.lang.String">1</Value>
</Feature>
<Feature>
  <Name className="java.lang.String">kind</Name>
  <Value className="java.lang.String">space</Value>
</Feature>
</Annotation>
<Annotation Id="19" Type="Token" StartNode="39" EndNode="40">
<Feature>
  <Name className="java.lang.String">length</Name>
  <Value className="java.lang.String">1</Value>
</Feature>
<Feature>
  <Name className="java.lang.String">orth</Name>
  <Value className="java.lang.String">lowercase</Value>
</Feature>
<Feature>
  <Name className="java.lang.String">string</Name>
  <Value className="java.lang.String">a</Value>
</Feature>
<Feature>
  <Name className="java.lang.String">category</Name>
  <Value className="java.lang.String">DT</Value>
</Feature>
<Feature>
  <Name className="java.lang.String">kind</Name>
  <Value className="java.lang.String">word</Value>
</Feature>
</Annotation>
<Annotation Id="20" Type="SpaceToken" StartNode="40" EndNode="41">
<Feature>
  <Name className="java.lang.String">string</Name>
  <Value className="java.lang.String"> </Value>
</Feature>
<Feature>
  <Name className="java.lang.String">length</Name>
  <Value className="java.lang.String">1</Value>
</Feature>
<Feature>
  <Name className="java.lang.String">kind</Name>
  <Value className="java.lang.String">space</Value>
</Feature>
</Annotation>
<Annotation Id="21" Type="Token" StartNode="41" EndNode="44">
<Feature>
  <Name className="java.lang.String">length</Name>
  <Value className="java.lang.String">3</Value>
</Feature>
<Feature>
  <Name className="java.lang.String">orth</Name>
  <Value className="java.lang.String">allCaps</Value>
</Feature>
<Feature>
  <Name className="java.lang.String">origString</Name>
  <Value className="java.lang.String">DBA</Value>
</Feature>
<Feature>
  <Name className="java.lang.String">string</Name>
  <Value className="java.lang.String">DBA</Value>
</Feature>
<Feature>
  <Name className="java.lang.String">category</Name>
  <Value className="java.lang.String">NNP</Value>
</Feature>
<Feature>
  <Name className="java.lang.String">kind</Name>
  <Value className="java.lang.String">word</Value>
</Feature>
</Annotation>
<Annotation Id="22" Type="Token" StartNode="44" EndNode="45">
<Feature>
  <Name className="java.lang.String">length</Name>
  <Value className="java.lang.String">1</Value>
</Feature>
<Feature>
  <Name className="java.lang.String">string</Name>
  <Value className="java.lang.String">.</Value>
</Feature>
<Feature>
  <Name className="java.lang.String">category</Name>
  <Value className="java.lang.String">.</Value>
</Feature>
<Feature>
  <Name className="java.lang.String">kind</Name>
  <Value className="java.lang.String">punctuation</Value>
</Feature>
</Annotation>
<Annotation Id="25" Type="SpaceToken" StartNode="45" EndNode="46">
<Feature>
  <Name className="java.lang.String">string</Name>
  <Value className="java.lang.String">
</Value>
</Feature>
<Feature>
  <Name className="java.lang.String">length</Name>
  <Value className="java.lang.String">1</Value>
</Feature>
<Feature>
  <Name className="java.lang.String">kind</Name>
  <Value className="java.lang.String">control</Value>
</Feature>
</Annotation>
<Annotation Id="26" Type="SpaceToken" StartNode="46" EndNode="47">
<Feature>
  <Name className="java.lang.String">string</Name>
  <Value className="java.lang.String">
</Value>
</Feature>
<Feature>
  <Name className="java.lang.String">length</Name>
  <Value className="java.lang.String">1</Value>
</Feature>
<Feature>
  <Name className="java.lang.String">kind</Name>
  <Value className="java.lang.String">control</Value>
</Feature>
</Annotation>
<Annotation Id="65" Type="Lookup" StartNode="17" EndNode="21">
<Feature>
  <Name className="java.lang.String">majorType</Name>
  <Value className="java.lang.String">time_modifier</Value>
</Feature>
</Annotation>
<Annotation Id="66" Type="Lookup" StartNode="22" EndNode="24">
<Feature>
  <Name className="java.lang.String">majorType</Name>
  <Value className="java.lang.String">country_code</Value>
</Feature>
</Annotation>
<Annotation Id="67" Type="Split" StartNode="14" EndNode="17">
<Feature>
  <Name className="java.lang.String">kind</Name>
  <Value className="java.lang.String">internal</Value>
</Feature>
</Annotation>
<Annotation Id="68" Type="Split" StartNode="44" EndNode="45">
<Feature>
  <Name className="java.lang.String">kind</Name>
  <Value className="java.lang.String">internal</Value>
</Feature>
</Annotation>
<Annotation Id="69" Type="Split" StartNode="45" EndNode="47">
<Feature>
  <Name className="java.lang.String">kind</Name>
  <Value className="java.lang.String">external</Value>
</Feature>
</Annotation>
<Annotation Id="70" Type="Sentence" StartNode="0" EndNode="17">
</Annotation>
<Annotation Id="71" Type="Sentence" StartNode="17" EndNode="45">
</Annotation>
<Annotation Id="78" Type="Unknown" StartNode="41" EndNode="44">
<Feature>
  <Name className="java.lang.String">rule</Name>
  <Value className="java.lang.String">Unknown</Value>
</Feature>
<Feature>
  <Name className="java.lang.String">kind</Name>
  <Value className="java.lang.String">PN</Value>
</Feature>
</Annotation>
</AnnotationSet>

<!-- Named annotation set -->

<AnnotationSet Name="Original markups">
<Annotation Id="0" Type="Tweet" StartNode="0" EndNode="45">
<Feature>
  <Name className="java.lang.String">quoted_status</Name>
  <Value className="gate.corpora.ObjectWrapper"><![CDATA[<?xml version='1.0' encoding='UTF-8'?><gate.corpora.ObjectWrapper><value class="gate.util.SimpleFeatureMapImpl" serialization="custom"><gate.util.SimpleMapImpl><default><capacity>48</capacity><count>31</count><theKeys><string>extended_tweet</string><string>in_reply_to_status_id_str</string><string>in_reply_to_status_id</string><string>created_at</string><string>in_reply_to_user_id_str</string><string>source</string><string>quoted_status_id</string><string>retweet_count</string><string>retweeted</string><string>geo</string><string>filter_level</string><string>in_reply_to_screen_name</string><string>is_quote_status</string><string>id_str</string><string>in_reply_to_user_id</string><string>favorite_count</string><string>id</string><string>text</string><string>place</string><string>lang</string><string>quote_count</string><string>favorited</string><string>possibly_sensitive</string><string>coordinates</string><string>truncated</string><string>reply_count</string><string>entities</string><string>display_text_range</string><string>quoted_status_id_str</string><string>contributors</string><string>user</string><null/><null/><null/><null/><null/><null/><null/><null/><null/><null/><null/><null/><null/><null/><null/><null/><null/></theKeys><theValues><gate.util.SimpleFeatureMapImpl serialization="custom"><gate.util.SimpleMapImpl><default><capacity>3</capacity><count>3</count><theKeys><string>entities</string><string>full_text</string><string>display_text_range</string></theKeys><theValues><gate.util.SimpleFeatureMapImpl serialization="custom"><gate.util.SimpleMapImpl><default><capacity>6</capacity><count>4</count><theKeys><string>urls</string><string>hashtags</string><string>user_mentions</string><string>symbols</string><null/><null/></theKeys><theValues><list><gate.util.SimpleFeatureMapImpl serialization="custom"><gate.util.SimpleMapImpl><default><capacity>6</capacity><count>4</count><theKeys><string>display_url</string><string>indices</string><string>expanded_url</string><string>url</string><null/><null/></theKeys><theValues><string>twitter.com/jericon/status…</string><list><int>284</int><int>307</int></list><string>https://twitter.com/jericon/status/1105875153831878657</string><string>https://t.co/WUd6Cmw6yn</string><null/><null/></theValues></default></gate.util.SimpleMapImpl></gate.util.SimpleFeatureMapImpl></list><list/><list/><list/><null/><null/></theValues></default></gate.util.SimpleMapImpl></gate.util.SimpleFeatureMapImpl><string>This conversation between ex-Twitter-DBAs is why I love and respect DBAs. Scroll to the top and read down the replies. Then, click on Lisa’s original tweet at the top and read the _other_ replies. If you underestimate or disrespect the people who keep your data safe &amp;amp; available… https://t.co/WUd6Cmw6yn</string><list><int>0</int><int>283</int></list></theValues></default></gate.util.SimpleMapImpl></gate.util.SimpleFeatureMapImpl><null/><null/><string>Thu Mar 14 15:05:11 +0000 2019</string><null/><string>&lt;a href="https://tapbots.com/software/tweetbot/mac" rel="nofollow">Tweetbot for Mac&lt;/a></string><string>1105875153831878657</string><int>17</int><boolean>false</boolean><null/><string>low</string><null/><boolean>true</boolean><string>1106209667187912706</string><null/><int>52</int><string>1106209667187912706</string><string>This conversation between ex-Twitter-DBAs is why I love and respect DBAs. Scroll to the top and read down the repli… https://t.co/ayoj378R6A</string><null/><string>en</string><int>1</int><boolean>false</boolean><boolean>false</boolean><null/><boolean>true</boolean><int>4</int><gate.util.SimpleFeatureMapImpl serialization="custom"><gate.util.SimpleMapImpl><default><capacity>6</capacity><count>4</count><theKeys><string>urls</string><string>hashtags</string><string>user_mentions</string><string>symbols</string><null/><null/></theKeys><theValues><list><gate.util.SimpleFeatureMapImpl serialization="custom"><gate.util.SimpleMapImpl><default><capacity>6</capacity><count>4</count><theKeys><string>display_url</string><string>indices</string><string>expanded_url</string><string>url</string><null/><null/></theKeys><theValues><string>twitter.com/i/web/status/1…</string><list><int>117</int><int>140</int></list><string>https://twitter.com/i/web/status/1106209667187912706</string><string>https://t.co/ayoj378R6A</string><null/><null/></theValues></default></gate.util.SimpleMapImpl></gate.util.SimpleFeatureMapImpl></list><list/><list/><list/><null/><null/></theValues></default></gate.util.SimpleMapImpl></gate.util.SimpleFeatureMapImpl><list><int>0</int><int>140</int></list><string>1105875153831878657</string><null/><gate.util.SimpleFeatureMapImpl serialization="custom"><gate.util.SimpleMapImpl><default><capacity>48</capacity><count>39</count><theKeys><string>utc_offset</string><string>friends_count</string><string>profile_image_url_https</string><string>listed_count</string><string>profile_background_image_url</string><string>default_profile_image</string><string>favourites_count</string><string>description</string><string>created_at</string><string>is_translator</string><string>profile_background_image_url_https</string><string>protected</string><string>screen_name</string><string>id_str</string><string>profile_link_color</string><string>translator_type</string><string>id</string><string>geo_enabled</string><string>profile_background_color</string><string>lang</string><string>profile_sidebar_border_color</string><string>profile_text_color</string><string>verified</string><string>profile_image_url</string><string>time_zone</string><string>url</string><string>contributors_enabled</string><string>profile_background_tile</string><string>profile_banner_url</string><string>statuses_count</string><string>follow_request_sent</string><string>followers_count</string><string>profile_use_background_image</string><string>default_profile</string><string>following</string><string>name</string><string>location</string><string>profile_sidebar_fill_color</string><string>notifications</string><null/><null/><null/><null/><null/><null/><null/><null/><null/></theKeys><theValues><null/><int>103</int><string>https://pbs.twimg.com/profile_images/1062705123225411584/uRheCEkM_normal.jpg</string><int>398</int><string>http://abs.twimg.com/images/themes/theme15/bg.png</string><boolean>false</boolean><int>27</int><string>CTO @VividCortex. Working on personal growth &amp; making a difference. Silence is violence, but a little learning is a dangerous thing. He/him.</string><string>Thu Apr 02 12:08:55 +0000 2009</string><boolean>false</boolean><string>https://abs.twimg.com/images/themes/theme15/bg.png</string><boolean>false</boolean><string>xaprb</string><string>28325059</string><string>0084B4</string><string>none</string><int>28325059</int><boolean>false</boolean><string>022330</string><string>en</string><string>A8C7F7</string><string>333333</string><boolean>true</boolean><string>http://pbs.twimg.com/profile_images/1062705123225411584/uRheCEkM_normal.jpg</string><null/><string>https://www.vividcortex.com</string><boolean>false</boolean><boolean>false</boolean><string>https://pbs.twimg.com/profile_banners/28325059/1552317159</string><int>845</int><null/><int>8547</int><boolean>true</boolean><boolean>false</boolean><null/><string>Baron Sc​hwartz</string><string>Here, now</string><string>C0DFEC</string><null/><null/><null/><null/><null/><null/><null/><null/><null/><null/></theValues></default></gate.util.SimpleMapImpl></gate.util.SimpleFeatureMapImpl><null/><null/><null/><null/><null/><null/><null/><null/><null/><null/><null/><null/><null/><null/><null/><null/><null/></theValues></default></gate.util.SimpleMapImpl></value></gate.corpora.ObjectWrapper>]]></Value>
</Feature>
<Feature>
  <Name className="java.lang.String">created_at</Name>
  <Value className="java.lang.String">Thu Mar 14 18:27:04 +0000 2019</Value>
</Feature>
<Feature>
  <Name className="java.lang.String">source</Name>
  <Value className="java.lang.String">&lt;a href="http://twitter.com/download/android" rel="nofollow">Twitter for Android&lt;/a></Value>
</Feature>
<Feature>
  <Name className="java.lang.String">quoted_status_id</Name>
  <Value className="java.lang.String">1106209667187912706</Value>
</Feature>
<Feature>
  <Name className="java.lang.String">retweet_count</Name>
  <Value className="java.lang.Integer">0</Value>
</Feature>
<Feature>
  <Name className="java.lang.String">retweeted</Name>
  <Value className="java.lang.Boolean">false</Value>
</Feature>
<Feature>
  <Name className="java.lang.String">filter_level</Name>
  <Value className="java.lang.String">low</Value>
</Feature>
<Feature>
  <Name className="java.lang.String">is_quote_status</Name>
  <Value className="java.lang.Boolean">true</Value>
</Feature>
<Feature>
  <Name className="java.lang.String">id_str</Name>
  <Value className="java.lang.String">1106260472465145857</Value>
</Feature>
<Feature>
  <Name className="java.lang.String">favorite_count</Name>
  <Value className="java.lang.Integer">0</Value>
</Feature>
<Feature>
  <Name className="java.lang.String">id</Name>
  <Value className="java.lang.String">1106260472465145857</Value>
</Feature>
<Feature>
  <Name className="java.lang.String">place</Name>
  <Value className="gate.corpora.ObjectWrapper"><![CDATA[<?xml version='1.0' encoding='UTF-8'?><gate.corpora.ObjectWrapper><value class="gate.util.SimpleFeatureMapImpl" serialization="custom"><gate.util.SimpleMapImpl><default><capacity>12</capacity><count>9</count><theKeys><string>country_code</string><string>country</string><string>full_name</string><string>bounding_box</string><string>place_type</string><string>name</string><string>attributes</string><string>id</string><string>url</string><null/><null/><null/></theKeys><theValues><string>ES</string><string>España</string><string>Madrid, España</string><gate.util.SimpleFeatureMapImpl serialization="custom"><gate.util.SimpleMapImpl><default><capacity>3</capacity><count>2</count><theKeys><string>coordinates</string><string>type</string><null/></theKeys><theValues><list><list><list><double>-3.889005</double><double>40.312071</double></list><list><double>-3.889005</double><double>40.643518</double></list><list><double>-3.51801</double><double>40.643518</double></list><list><double>-3.51801</double><double>40.312071</double></list></list></list><string>Polygon</string><null/></theValues></default></gate.util.SimpleMapImpl></gate.util.SimpleFeatureMapImpl><string>city</string><string>Madrid</string><gate.util.SimpleFeatureMapImpl serialization="custom"><gate.util.SimpleMapImpl><default><capacity>3</capacity><count>0</count><theKeys><null/><null/><null/></theKeys><theValues><null/><null/><null/></theValues></default></gate.util.SimpleMapImpl></gate.util.SimpleFeatureMapImpl><string>206c436ce43a43a3</string><string>https://api.twitter.com/1.1/geo/id/206c436ce43a43a3.json</string><null/><null/><null/></theValues></default></gate.util.SimpleMapImpl></value></gate.corpora.ObjectWrapper>]]></Value>
</Feature>
<Feature>
  <Name className="java.lang.String">quoted_status_permalink</Name>
  <Value className="gate.corpora.ObjectWrapper"><![CDATA[<?xml version='1.0' encoding='UTF-8'?><gate.corpora.ObjectWrapper><value class="gate.util.SimpleFeatureMapImpl" serialization="custom"><gate.util.SimpleMapImpl><default><capacity>3</capacity><count>3</count><theKeys><string>expanded</string><string>display</string><string>url</string></theKeys><theValues><string>https://twitter.com/xaprb/status/1106209667187912706</string><string>twitter.com/xaprb/status/1…</string><string>https://t.co/9Ibhv2V1r4</string></theValues></default></gate.util.SimpleMapImpl></value></gate.corpora.ObjectWrapper>]]></Value>
</Feature>
<Feature>
  <Name className="java.lang.String">lang</Name>
  <Value className="java.lang.String">en</Value>
</Feature>
<Feature>
  <Name className="java.lang.String">quote_count</Name>
  <Value className="java.lang.Integer">0</Value>
</Feature>
<Feature>
  <Name className="java.lang.String">favorited</Name>
  <Value className="java.lang.Boolean">false</Value>
</Feature>
<Feature>
  <Name className="java.lang.String">truncated</Name>
  <Value className="java.lang.Boolean">false</Value>
</Feature>
<Feature>
  <Name className="java.lang.String">timestamp_ms</Name>
  <Value className="java.lang.String">1552588024618</Value>
</Feature>
<Feature>
  <Name className="java.lang.String">reply_count</Name>
  <Value className="java.lang.Integer">0</Value>
</Feature>
<Feature>
  <Name className="java.lang.String">entities</Name>
  <Value className="gate.corpora.ObjectWrapper"><![CDATA[<?xml version='1.0' encoding='UTF-8'?><gate.corpora.ObjectWrapper><value class="gate.util.SimpleFeatureMapImpl" serialization="custom"><gate.util.SimpleMapImpl><default><capacity>6</capacity><count>4</count><theKeys><string>urls</string><string>hashtags</string><string>user_mentions</string><string>symbols</string><null/><null/></theKeys><theValues><list/><list/><list/><list/><null/><null/></theValues></default></gate.util.SimpleMapImpl></value></gate.corpora.ObjectWrapper>]]></Value>
</Feature>
<Feature>
  <Name className="java.lang.String">quoted_status_id_str</Name>
  <Value className="java.lang.String">1106209667187912706</Value>
</Feature>
<Feature>
  <Name className="java.lang.String">user</Name>
  <Value className="gate.corpora.ObjectWrapper"><![CDATA[<?xml version='1.0' encoding='UTF-8'?><gate.corpora.ObjectWrapper><value class="gate.util.SimpleFeatureMapImpl" serialization="custom"><gate.util.SimpleMapImpl><default><capacity>48</capacity><count>39</count><theKeys><string>utc_offset</string><string>friends_count</string><string>profile_image_url_https</string><string>listed_count</string><string>profile_background_image_url</string><string>default_profile_image</string><string>favourites_count</string><string>description</string><string>created_at</string><string>is_translator</string><string>profile_background_image_url_https</string><string>protected</string><string>screen_name</string><string>id_str</string><string>profile_link_color</string><string>translator_type</string><string>id</string><string>geo_enabled</string><string>profile_background_color</string><string>lang</string><string>profile_sidebar_border_color</string><string>profile_text_color</string><string>verified</string><string>profile_image_url</string><string>time_zone</string><string>url</string><string>contributors_enabled</string><string>profile_background_tile</string><string>profile_banner_url</string><string>statuses_count</string><string>follow_request_sent</string><string>followers_count</string><string>profile_use_background_image</string><string>default_profile</string><string>following</string><string>name</string><string>location</string><string>profile_sidebar_fill_color</string><string>notifications</string><null/><null/><null/><null/><null/><null/><null/><null/><null/></theKeys><theValues><null/><int>241</int><string>https://pbs.twimg.com/profile_images/867991061146161152/pb6jmRGY_normal.jpg</string><int>3</int><string>http://abs.twimg.com/images/themes/theme1/bg.png</string><boolean>false</boolean><int>6942</int><string>I run for something better. Data Engineer MySQL based systems, NoSQL or any DB to be managed</string><string>Sat Feb 09 11:46:03 +0000 2008</string><boolean>false</boolean><string>https://abs.twimg.com/images/themes/theme1/bg.png</string><boolean>false</boolean><string>rmateos</string><string>13279322</string><string>87B6E8</string><string>none</string><int>13279322</int><boolean>true</boolean><string>F5F5F5</string><string>es</string><string>FFFFFF</string><string>333333</string><boolean>false</boolean><string>http://pbs.twimg.com/profile_images/867991061146161152/pb6jmRGY_normal.jpg</string><null/><null/><boolean>false</boolean><boolean>false</boolean><string>https://pbs.twimg.com/profile_banners/13279322/1469139154</string><int>8664</int><null/><int>95</int><boolean>true</boolean><boolean>false</boolean><null/><string>rmateos</string><string>Madrid</string><string>DDEEF6</string><null/><null/><null/><null/><null/><null/><null/><null/><null/><null/></theValues></default></gate.util.SimpleMapImpl></value></gate.corpora.ObjectWrapper>]]></Value>
</Feature>
</Annotation>
</AnnotationSet>

<!-- Named annotation set -->

<AnnotationSet Name="Sentiment">
</AnnotationSet>

</GateDocument>
